
{
  "ID": 121,
  "Name": "Bloodied Hills",
  "Resource Location": "spookybiomes:bloodied_hills",
  "Class": "com.mcmoddev.spookybiomes.common.world.biome.BiomeBloodiedHills",
  "Root Height": 0.01,
  "Height Variation": 0.5,
  "Top Block": "spookybiomes:bloodied_grass[snowy\u003dfalse]",
  "Filler Block": "spookybiomes:bloodied_dirt",
  "Ocean Top Block": "Disabled. Activate in BiomeTweakerCore.",
  "Ocean Filler Block": "Disabled. Activate in BiomeTweakerCore.",
  "Actual Filler Blocks": [
    "minecraft:stone[variant\u003dstone]"
  ],
  "Grass Color": "Not set. Check in-game.",
  "Foliage Color": "Not set. Check in-game.",
  "Water Color": "9371648",
  "Temperature": 0.5,
  "Humidity": 0.5,
  "Water Tint": 9371648,
  "Enable Rain": true,
  "Enable Snow": false,
  "Dictionary Types": [
    "FOREST",
    "WET"
  ],
  "BiomeManager Entries": {
    "WARM Weights": [
      15
    ]
  },
  "Spawnable Creatures": [
    {
      "Entity Class": "net.minecraft.entity.monster.EntityVex",
      "Weight": 1,
      "Min Group Count": 1,
      "Max Group Count": 2
    },
    {
      "Entity Class": "com.mcmoddev.spookybiomes.common.entity.EntityTheForgottenWarlock",
      "Weight": 1,
      "Min Group Count": 1,
      "Max Group Count": 2
    }
  ],
  "Spawnable Monsters": [
    {
      "Entity Class": "net.minecraft.entity.monster.EntitySpider",
      "Weight": 100,
      "Min Group Count": 4,
      "Max Group Count": 4
    },
    {
      "Entity Class": "net.minecraft.entity.monster.EntityZombie",
      "Weight": 95,
      "Min Group Count": 4,
      "Max Group Count": 4
    },
    {
      "Entity Class": "net.minecraft.entity.monster.EntityZombieVillager",
      "Weight": 5,
      "Min Group Count": 1,
      "Max Group Count": 1
    },
    {
      "Entity Class": "net.minecraft.entity.monster.EntitySkeleton",
      "Weight": 100,
      "Min Group Count": 4,
      "Max Group Count": 4
    },
    {
      "Entity Class": "net.minecraft.entity.monster.EntityCreeper",
      "Weight": 100,
      "Min Group Count": 4,
      "Max Group Count": 4
    },
    {
      "Entity Class": "net.minecraft.entity.monster.EntitySlime",
      "Weight": 100,
      "Min Group Count": 4,
      "Max Group Count": 4
    },
    {
      "Entity Class": "net.minecraft.entity.monster.EntityEnderman",
      "Weight": 10,
      "Min Group Count": 1,
      "Max Group Count": 4
    },
    {
      "Entity Class": "net.minecraft.entity.monster.EntityWitch",
      "Weight": 5,
      "Min Group Count": 1,
      "Max Group Count": 1
    },
    {
      "Entity Class": "com.jamieswhiteshirt.trumpetskeleton.common.entity.EntityTrumpetSkeleton",
      "Weight": 25,
      "Min Group Count": 4,
      "Max Group Count": 4
    },
    {
      "Entity Class": "com.mrbysco.instrumentalmobs.entities.EntityMaracaSpider",
      "Weight": 20,
      "Min Group Count": 4,
      "Max Group Count": 4
    },
    {
      "Entity Class": "com.mrbysco.instrumentalmobs.entities.EntityDrumZombie",
      "Weight": 19,
      "Min Group Count": 4,
      "Max Group Count": 4
    },
    {
      "Entity Class": "com.mrbysco.instrumentalmobs.entities.EntityFrenchHornCreeper",
      "Weight": 20,
      "Min Group Count": 4,
      "Max Group Count": 4
    },
    {
      "Entity Class": "com.mrbysco.instrumentalmobs.entities.EntityTubaEnderman",
      "Weight": 2,
      "Min Group Count": 1,
      "Max Group Count": 4
    }
  ],
  "Spawnable Water Creatures": [
    {
      "Entity Class": "net.minecraft.entity.passive.EntitySquid",
      "Weight": 10,
      "Min Group Count": 4,
      "Max Group Count": 4
    }
  ],
  "Spawnable Cave Creatures": [
    {
      "Entity Class": "net.minecraft.entity.passive.EntityBat",
      "Weight": 10,
      "Min Group Count": 8,
      "Max Group Count": 8
    }
  ],
  "Spawn Biome": true,
  "Tweaked": true,
  "BOP Generators": {
    "FLOWERS Generators": [
      {
        "ID": "flora",
        "Name": "glowshrooms"
      },
      {
        "ID": "flora",
        "Name": "miners_delight"
      },
      {
        "ID": "flora",
        "Name": "roots"
      }
    ]
  },
  "BOP Owner": "OTHER",
  "BOP Weight Map": {},
  "BOP Climate Weights": {
    "WET_TEMPERATE": [
      15
    ],
    "DRY_TEMPERATE": [
      15
    ],
    "WARM_TEMPERATE": [
      15
    ],
    "HOT_SWAMP": [
      15
    ],
    "MEDITERANEAN": [
      15
    ]
  },
  "BOP Island Weight": 0
}